{"cameraMode":{"drawMode":0,"name":"Shaded","section":"Shading Mode"},"sceneLighting":true,"audioPlay":false,"sceneViewState":{"m_AlwaysRefresh":false,"showFog":true,"showSkybox":true,"showFlares":true,"showImageEffects":true,"showParticleSystems":true,"showVisualEffectGraphs":true,"m_FxEnabled":true},"in2DMode":false,"pivot":{"x":35.819374084472659,"y":24.084930419921876,"z":23.300424575805665},"rotation":{"x":-0.16349774599075318,"y":0.698599636554718,"z":-0.16894803941249848,"w":-0.6758922934532166},"size":8.044865608215332,"orthographic":false}